cachecraft/__init__.py
cachecraft/cache.py
CacheCraft-0.1.2.dist-info/LICENSE
CacheCraft-0.1.2.dist-info/METADATA
CacheCraft-0.1.2.dist-info/WHEEL
CacheCraft-0.1.2.dist-info/top_level.txt
CacheCraft-0.1.2.dist-info/RECORD
