Metadata-Version: 2.1
Name: CacheCraft
Version: 0.1.2
Summary: A simple in-memory caching module like Memcached
Home-page: https://github.com/Aditya-1998k/CacheCraft
Author: Aditya Gupta
Author-email: aditya98gupta@gmail.com
Classifier: Programming Language :: Python :: 3
Classifier: License :: OSI Approved :: MIT License
Classifier: Operating System :: OS Independent
Requires-Python: >=3.6
License-File: LICENSE
